pymapf/__init__.py
pymapf/centralized/__init__.py
pymapf/centralized/animator.py
pymapf/centralized/common.py
pymapf/centralized/world.py
pymapf/centralized/cooperative_astar/__init__.py
pymapf/centralized/cooperative_astar/agent.py
pymapf/centralized/cooperative_astar/astar.py
pymapf/centralized/cooperative_astar/cooperative_astar.py
pymapf/centralized/cooperative_astar/node.py
pymapf/centralized/cooperative_astar/state.py
pymapf/decentralized/__init__.py
pymapf/decentralized/obstacle.py
pymapf/decentralized/position.py
pymapf/decentralized/nmpc/__init__.py
pymapf/decentralized/nmpc/nmpc.py
pymapf/decentralized/nmpc/nmpc_agent.py
pymapf/decentralized/velocity_obstacle/__init__.py
pymapf/decentralized/velocity_obstacle/velocity_agent.py
pymapf/decentralized/velocity_obstacle/velocity_obstacle.py
pymapf-0.1.3.dist-info/LICENSE
pymapf-0.1.3.dist-info/METADATA
pymapf-0.1.3.dist-info/WHEEL
pymapf-0.1.3.dist-info/top_level.txt
pymapf-0.1.3.dist-info/RECORD
