Metadata-Version: 2.1
Name: pymapf
Version: 0.1.3
Summary: Pymapf is a library for decentralized and centralized multi-agent planning tools
Home-page: https://github.com/apla-toolbox/pymapf
Author: Erwin Lejeune
Author-email: erwinlejeune.pro@gmail.com
License: UNKNOWN
Platform: UNKNOWN
Classifier: Programming Language :: Python :: 3 :: Only
Classifier: Programming Language :: Python :: 3.6
Classifier: Programming Language :: Python :: 3.7
Classifier: Programming Language :: Python :: 3.8
Classifier: Programming Language :: Python :: 3
Classifier: License :: OSI Approved :: Apache Software License
Classifier: Operating System :: Unix
Classifier: Operating System :: MacOS
Classifier: Framework :: Pytest
Requires-Python: >=3.6
Requires-Dist: numpy (==1.19.5)
Requires-Dist: scipy (==1.6.0)
Requires-Dist: coloredlogs (==15.0)
Requires-Dist: matplotlib (==3.3.3)
Requires-Dist: termcolor (==1.1.0)
